{"skeleton":{"hash":"e70gLOrTtVgbesmnTzgeNkmCjdY","spine":"3.8.72","images":"./images/","audio":""},"bones":[{"name":"root"},{"name":"revive_fx1/10","parent":"root","length":300,"rotation":-90.75,"x":-2.85,"y":1838.86,"scaleX":2.6352,"color":"01ff66ff"},{"name":"revive_fx/1","parent":"root","x":132.54,"y":287.45,"color":"b487ffff"}],"slots":[{"name":"revive_fx1/10","bone":"revive_fx1/10","blend":"additive"},{"name":"revive_fx/1","bone":"revive_fx/1"}],"skins":[{"name":"default","attachments":{"revive_fx/1":{"revive_fx/1":{"x":0.54,"y":-5.88,"width":400,"height":400},"revive_fx/2":{"x":0.54,"y":-5.88,"width":400,"height":400},"revive_fx/3":{"x":0.54,"y":-5.88,"width":400,"height":400},"revive_fx/4":{"x":0.54,"y":-5.88,"width":400,"height":400},"revive_fx/5":{"x":0.54,"y":-5.88,"width":400,"height":400},"revive_fx/6":{"x":0.54,"y":-5.88,"width":400,"height":400},"revive_fx/7":{"x":0.54,"y":-5.88,"width":400,"height":400},"revive_fx/8":{"x":0.54,"y":-5.88,"width":400,"height":400},"revive_fx/9":{"x":0.54,"y":-5.88,"width":400,"height":400},"revive_fx/10":{"x":0.54,"y":-5.88,"width":400,"height":400},"revive_fx/11":{"x":0.54,"y":-5.88,"width":400,"height":400},"revive_fx/12":{"x":0.54,"y":-5.88,"width":400,"height":400},"revive_fx/13":{"x":0.54,"y":-5.88,"width":400,"height":400},"revive_fx/14":{"x":0.54,"y":-5.88,"width":400,"height":400},"revive_fx/15":{"x":0.54,"y":-5.88,"width":400,"height":400}},"revive_fx1/10":{"revive_fx1/1":{"x":353.28,"y":-12.28,"rotation":90.75,"width":682,"height":687},"revive_fx1/2":{"x":353.28,"y":-12.28,"rotation":90.75,"width":682,"height":687},"revive_fx1/3":{"x":353.28,"y":-12.28,"rotation":90.75,"width":682,"height":687},"revive_fx1/4":{"x":353.28,"y":-12.28,"rotation":90.75,"width":682,"height":687},"revive_fx1/5":{"x":353.28,"y":-12.28,"rotation":90.75,"width":682,"height":687},"revive_fx1/6":{"x":353.28,"y":-12.28,"rotation":90.75,"width":682,"height":687},"revive_fx1/7":{"x":353.28,"y":-12.28,"rotation":90.75,"width":682,"height":687},"revive_fx1/8":{"x":353.28,"y":-12.28,"rotation":90.75,"width":682,"height":687},"revive_fx1/9":{"x":353.28,"y":-12.28,"rotation":90.75,"width":682,"height":687},"revive_fx1/10":{"x":353.28,"y":-12.28,"rotation":90.75,"width":682,"height":687},"revive_fx1/11":{"x":353.28,"y":-12.28,"rotation":90.75,"width":682,"height":687},"revive_fx1/12":{"x":353.28,"y":-12.28,"rotation":90.75,"width":682,"height":687},"revive_fx1/13":{"x":353.28,"y":-12.28,"rotation":90.75,"width":682,"height":687},"revive_fx1/14":{"x":353.28,"y":-12.28,"rotation":90.75,"width":682,"height":687}}}}],"animations":{"fx_revive":{"slots":{"revive_fx/1":{"attachment":[{"time":2,"name":"revive_fx/1"},{"time":2.0333,"name":"revive_fx/2"},{"time":2.0667,"name":"revive_fx/3"},{"time":2.1,"name":"revive_fx/4"},{"time":2.1333,"name":"revive_fx/5"},{"time":2.1667,"name":"revive_fx/6"},{"time":2.2,"name":"revive_fx/7"},{"time":2.2333,"name":"revive_fx/8"},{"time":2.2667,"name":"revive_fx/9"},{"time":2.3,"name":"revive_fx/10"},{"time":2.3333,"name":"revive_fx/11"},{"time":2.3667,"name":"revive_fx/13"},{"time":2.4,"name":"revive_fx/14"},{"time":2.4333,"name":"revive_fx/15"},{"time":2.4667,"name":null}]},"revive_fx1/10":{"attachment":[{"name":"revive_fx1/14"},{"time":0.6667,"name":"revive_fx1/1"},{"time":0.7333,"name":"revive_fx1/2"},{"time":0.8,"name":"revive_fx1/3"},{"time":0.8667,"name":"revive_fx1/4"},{"time":0.9333,"name":"revive_fx1/5"},{"time":1,"name":"revive_fx1/6"},{"time":1.0667,"name":"revive_fx1/7"},{"time":1.1333,"name":"revive_fx1/8"},{"time":1.2,"name":"revive_fx1/9"},{"time":1.2667,"name":"revive_fx1/10"},{"time":1.3333,"name":"revive_fx1/11"},{"time":1.4,"name":"revive_fx1/12"},{"time":1.4667,"name":"revive_fx1/13"},{"time":2,"name":null}]}},"bones":{"revive_fx1/10":{"translate":[{"x":34.88,"y":916.17,"curve":"stepped"},{"time":1.4667,"x":34.88,"y":916.17,"curve":0.39,"c2":0.01,"c3":0.625,"c4":0.99},{"time":2,"x":4.64,"y":-1504.26}],"scale":[{"x":0.169,"y":0.183,"curve":0.391,"c2":0.01,"c3":0.632},{"time":0.2,"x":1.507,"y":0.204,"curve":0.391,"c2":0.01,"c3":0.632},{"time":0.6667,"x":1.507,"curve":"stepped"},{"time":1.4667,"x":1.507,"curve":0.39,"c2":0.01,"c3":0.625,"c4":0.99},{"time":2,"x":0.184,"y":0.416}]},"revive_fx/1":{"translate":[{"time":2,"x":-109.39,"y":52.72}],"scale":[{"time":2,"x":4.389,"y":4.389}]}}}}}